{
    "title": { "first": "Business", "second": "Success", "third": "With <br />Technology" },
    "subtitle": "Our Skill",
    "description": "At NexonGreen, we combine technical expertise with creative thinking to deliver solutions that make a real impact. Our team is skilled across a wide range of modern technologies and platforms.",
    "items": [
        {
            "label": "Web Development",
            "value": "90"
        },
        {
            "label": "Mobile App Development",
            "value": "85"
        },
        {
            "label": "WordPress & CMS",
            "value": "88"
        },
        {
            "label": "Internet of Things (IoT)",
            "value": "75"
        },
        {
            "label": "Digital Forensics (FTK)",
            "value": "70"
        },
        {
            "label": "Artificial Intelligence",
            "value": "80"
        },
        {
            "label": "Portfolio Design",
            "value": "92"
        }
    ],
    "button": {
        "label": "More",
        "link": "/about"
    }
}
